{
  "project_info": {
    "project_number": "1014251331583",
    "project_id": "estock-353714",
    "storage_bucket": "estock-353714.appspot.com"
  },
  "client": [
    {
      "client_info": {
        "mobilesdk_app_id": "1:1014251331583:android:b0474071dffd44c29711ca",
        "android_client_info": {
          "package_name": "com.example.eStock"
        }
      },
      "oauth_client": [
        {
          "client_id": "1014251331583-16k8u1k1dn0d3dp85o1kqmlcb02jugaj.apps.googleusercontent.com",
          "client_type": 3
        }
      ],
      "api_key": [
        {
          "current_key": "AIzaSyBGhfOSoo4pdm-TXJhz7gN3nwA01vXWh8c"
        }
      ],
      "services": {
        "appinvite_service": {
          "other_platform_oauth_client": [
            {
              "client_id": "1014251331583-16k8u1k1dn0d3dp85o1kqmlcb02jugaj.apps.googleusercontent.com",
              "client_type": 3
            },
            {
              "client_id": "1014251331583-9ssbcdtv1t2khrv9jj474ve8gi8v3lio.apps.googleusercontent.com",
              "client_type": 2,
              "ios_info": {
                "bundle_id": "com.example.eStock"
              }
            }
          ]
        }
      }
    }
  ],
  "configuration_version": "1"
}